strip_markdown/__init__.py
strip_markdown/__main__.py
strip_markdown/strip_markdown.py
strip_markdown-1.3.dist-info/LICENSE.txt
strip_markdown-1.3.dist-info/METADATA
strip_markdown-1.3.dist-info/WHEEL
strip_markdown-1.3.dist-info/top_level.txt
strip_markdown-1.3.dist-info/RECORD
