Metadata-Version: 2.1
Name: strip_markdown
Version: 1.3
Summary: Converts markdown to plain text
Home-page: https://github.com/D3r3k23/strip_markdown
Author: Derek Henderson
Author-email: derekhenderson818@gmail.com
License: MIT License
Project-URL: Issues, https://github.com/D3r3k23/strip_markdown/issues
Keywords: markdown,md
Platform: OS Independent
Classifier: Development Status :: 5 - Production/Stable
Classifier: Programming Language :: Python :: 3
Classifier: License :: OSI Approved :: MIT License
Classifier: Operating System :: OS Independent
Requires-Python: >=3.10
License-File: LICENSE.txt
